notionary/__init__.py
notionary/blocks/__init__.py
notionary/blocks/client.py
notionary/blocks/enums.py
notionary/blocks/schemas.py
notionary/blocks/service.py
notionary/blocks/content/__init__.py
notionary/blocks/content/factory.py
notionary/blocks/content/service.py
notionary/comments/__init__.py
notionary/comments/client.py
notionary/comments/factory.py
notionary/comments/models.py
notionary/comments/schemas.py
notionary/comments/service.py
notionary/data_source/schemas.py
notionary/data_source/service.py
notionary/data_source/http/client.py
notionary/data_source/http/data_source_instance_client.py
notionary/data_source/properties/schemas.py
notionary/data_source/query/__init__.py
notionary/data_source/query/builder.py
notionary/data_source/query/resolver.py
notionary/data_source/query/schema.py
notionary/data_source/query/validator.py
notionary/data_source/schema/registry.py
notionary/data_source/schema/service.py
notionary/database/client.py
notionary/database/database_metadata_update_client.py
notionary/database/schemas.py
notionary/database/service.py
notionary/exceptions/__init__.py
notionary/exceptions/api.py
notionary/exceptions/base.py
notionary/exceptions/block_parsing.py
notionary/exceptions/file_upload.py
notionary/exceptions/properties.py
notionary/exceptions/search.py
notionary/exceptions/data_source/__init__.py
notionary/exceptions/data_source/builder.py
notionary/exceptions/data_source/properties.py
notionary/file_upload/__init__.py
notionary/file_upload/client.py
notionary/file_upload/models.py
notionary/file_upload/schemas.py
notionary/file_upload/service.py
notionary/file_upload/config/__init__.py
notionary/file_upload/config/config.py
notionary/file_upload/config/constants.py
notionary/file_upload/file/reader.py
notionary/file_upload/file_system/__init__.py
notionary/file_upload/file_system/models.py
notionary/file_upload/file_system/resolver.py
notionary/file_upload/query/__init__.py
notionary/file_upload/query/builder.py
notionary-0.5.3.dist-info/METADATA
notionary-0.5.3.dist-info/WHEEL
notionary-0.5.3.dist-info/licenses/LICENSE
notionary-0.5.3.dist-info/RECORD
