Metadata-Version: 2.4
Name: notionary
Version: 0.5.3
Summary: Python library for programmatic Notion workspace management - databases, pages, and content with advanced Markdown support
Project-URL: Homepage, https://github.com/mathisarends/notionary
Author-email: Mathis Arends <mathisarends27@gmail.com>
License: MIT
License-File: LICENSE
Requires-Python: >=3.12
Requires-Dist: aiofiles<25.0.0,>=24.1.0
Requires-Dist: httpx>=0.28.0
Requires-Dist: pydantic>=2.11.4
Requires-Dist: python-dotenv<2.0.0,>=1.0.1
